pyclam/__init__.py
pyclam/anomaly_detection/__init__.py
pyclam/anomaly_detection/anomaly_dataset.py
pyclam/anomaly_detection/anomaly_space.py
pyclam/anomaly_detection/chaoda.py
pyclam/anomaly_detection/graph_scorers.py
pyclam/anomaly_detection/meta_ml.py
pyclam/anomaly_detection/pretrained_models.py
pyclam/anomaly_detection/training.py
pyclam/classification/__init__.py
pyclam/classification/classifier.py
pyclam/core/__init__.py
pyclam/core/cluster.py
pyclam/core/cluster_criteria.py
pyclam/core/dataset.py
pyclam/core/graph.py
pyclam/core/graph_criteria.py
pyclam/core/metric.py
pyclam/core/space.py
pyclam/search/__init__.py
pyclam/search/cakes.py
pyclam/utils/__init__.py
pyclam/utils/constants.py
pyclam/utils/helpers.py
pyclam-0.8.0.dist-info/LICENSE
pyclam-0.8.0.dist-info/METADATA
pyclam-0.8.0.dist-info/WHEEL
pyclam-0.8.0.dist-info/top_level.txt
pyclam-0.8.0.dist-info/RECORD
