Metadata-Version: 2.1
Name: pyclam
Version: 0.8.0
Summary: Clustered Learning of Approximate Manifolds
Home-page: https://github.com/URI-ABD/clam
Author: Najib Ishaq <najib_ishaq@zoho.com>; Tom Howard <info@tomhoward.codes>; Noah Daniels <noah_daniels@uri.edu>; Morgan Prior <morgan_prior@uri.edu>; Isaac Chen <ijchen@uri.edu>; Oliver McLaughlin <olwmcjp@gmail.com>
Author-email: 
License: MIT
Requires-Python: >=3.9,<3.11
License-File: LICENSE
Requires-Dist: numpy (<1.23,>=1.22)
Requires-Dist: scipy (<1.9,>=1.8)
Requires-Dist: toml (<0.11,>=0.10)
Requires-Dist: scikit-learn (<1.2,>=1.1)
